[
    {
        "id": 1447833929977,
        "title": "codingplayboy",
        "text": "react vs angular"
    },
    {
        "id": 1472134095308,
        "title": "M",
        "text": "前端"
    },
    {
        "id": 1472135187314,
        "title": "W",
        "text": "#*测试*"
    },
    {
        "id": 1472136673630,
        "title": "random",
        "text": "凤凰"
    },
    {
        "id": 1483683584375,
        "title": "MVP",
        "text": "lihai"
    },
    {
        "id": 1483683665021,
        "title": "new",
        "text": "text"
    },
    {
        "id": 1483683711007,
        "title": "hahah",
        "text": "hahah"
    }
]